Metadata-Version: 1.1
Name: httpie-hmac-auth
Version: 0.2.0
Summary: HMAC Auth plugin for HTTPie.
Home-page: https://github.com/guardian/httpie-hmac-auth
Author: Nick Satterly
Author-email: nick.satterly@theguardian.com
License: MIT
Download-URL: https://github.com/guardian/httpie-hmac-auth
Platform: UNKNOWN
Classifier: Development Status :: 4 - Beta
Classifier: Programming Language :: Python
Classifier: Intended Audience :: Developers
Classifier: Environment :: Plugins
Classifier: License :: OSI Approved :: MIT License
Classifier: Topic :: Internet :: WWW/HTTP
Classifier: Topic :: Utilities
